{"trial_id": "0073", "hyperparameters": {"space": [{"class_name": "Int", "config": {"name": "num_layers", "default": null, "conditions": [], "min_value": 2, "max_value": 5, "step": 1, "sampling": "linear"}}, {"class_name": "Int", "config": {"name": "units_0", "default": null, "conditions": [], "min_value": 64, "max_value": 128, "step": 32, "sampling": "linear"}}, {"class_name": "Choice", "config": {"name": "activation", "default": "relu", "conditions": [], "values": ["relu", "selu", "tanh"], "ordered": false}}, {"class_name": "Float", "config": {"name": "l2_reg", "default": 1e-05, "conditions": [], "min_value": 1e-05, "max_value": 0.01, "step": null, "sampling": "log"}}, {"class_name": "Float", "config": {"name": "dropout_0", "default": 0.2, "conditions": [], "min_value": 0.2, "max_value": 0.5, "step": 0.1, "sampling": "linear"}}, {"class_name": "Int", "config": {"name": "units_1", "default": null, "conditions": [], "min_value": 64, "max_value": 128, "step": 32, "sampling": "linear"}}, {"class_name": "Float", "config": {"name": "dropout_1", "default": 0.2, "conditions": [], "min_value": 0.2, "max_value": 0.5, "step": 0.1, "sampling": "linear"}}, {"class_name": "Choice", "config": {"name": "optimizer", "default": "adam", "conditions": [], "values": ["adam", "rmsprop", "sgd"], "ordered": false}}, {"class_name": "Choice", "config": {"name": "learning_rate", "default": 0.01, "conditions": [], "values": [0.01, 0.001, 0.0001, 1e-05], "ordered": true}}, {"class_name": "Int", "config": {"name": "units_2", "default": null, "conditions": [], "min_value": 64, "max_value": 128, "step": 32, "sampling": "linear"}}, {"class_name": "Float", "config": {"name": "dropout_2", "default": 0.2, "conditions": [], "min_value": 0.2, "max_value": 0.5, "step": 0.1, "sampling": "linear"}}, {"class_name": "Int", "config": {"name": "units_3", "default": null, "conditions": [], "min_value": 64, "max_value": 128, "step": 32, "sampling": "linear"}}, {"class_name": "Float", "config": {"name": "dropout_3", "default": 0.2, "conditions": [], "min_value": 0.2, "max_value": 0.5, "step": 0.1, "sampling": "linear"}}, {"class_name": "Int", "config": {"name": "units_4", "default": null, "conditions": [], "min_value": 64, "max_value": 128, "step": 32, "sampling": "linear"}}, {"class_name": "Float", "config": {"name": "dropout_4", "default": 0.2, "conditions": [], "min_value": 0.2, "max_value": 0.5, "step": 0.1, "sampling": "linear"}}, {"class_name": "Float", "config": {"name": "momentum_sgd", "default": 0.0, "conditions": [], "min_value": 0.0, "max_value": 0.9, "step": null, "sampling": "linear"}}], "values": {"num_layers": 4, "units_0": 128, "activation": "relu", "l2_reg": 5.201991862210912e-05, "dropout_0": 0.4, "units_1": 64, "dropout_1": 0.2, "optimizer": "rmsprop", "learning_rate": 0.001, "units_2": 128, "dropout_2": 0.30000000000000004, "units_3": 96, "dropout_3": 0.30000000000000004, "units_4": 64, "dropout_4": 0.30000000000000004, "momentum_sgd": 0.44690713385032316, "tuner/epochs": 50, "tuner/initial_epoch": 17, "tuner/bracket": 2, "tuner/round": 2, "tuner/trial_id": "0067"}}, "metrics": {"metrics": {"loss": {"direction": "min", "observations": [{"value": [0.6897907853126526], "step": 32}]}, "accuracy": {"direction": "max", "observations": [{"value": [0.6699604988098145], "step": 32}]}, "val_loss": {"direction": "min", "observations": [{"value": [0.7585465312004089], "step": 32}]}, "val_accuracy": {"direction": "max", "observations": [{"value": [0.6226958632469177], "step": 32}]}}}, "score": 0.6226958632469177, "best_step": 32, "status": "COMPLETED", "message": null}